pip_plus/__init__.py
pip_plus/__version__.py
pip_plus/constants.py
pip_plus/entrypoint.py
pip_plus/logger.py
pip_plus/pinned_package.py
pip_plus/utils.py
test/__init__.py
test/requirements.txt
test/test_utils.py
pip_plus_cli-0.2.0.dist-info/METADATA
pip_plus_cli-0.2.0.dist-info/WHEEL
pip_plus_cli-0.2.0.dist-info/entry_points.txt
pip_plus_cli-0.2.0.dist-info/top_level.txt
pip_plus_cli-0.2.0.dist-info/zip-safe
pip_plus_cli-0.2.0.dist-info/RECORD
