Metadata-Version: 2.1
Name: pip-plus-cli
Version: 0.2.0
Summary: Pip-Plus
Home-page: https://github.com/Bee-Mar/pip-plus
Download-URL: https://github.com/Bee-Mar/pip-plus/archive/refs/tags/v0.2.0.tar.gz
Author: Brandon Marlowe
Author-email: bpmarlowe-software@protonmail.com
License: MIT
Keywords: pip pip-plus pip_plus
Requires-Python: >=3.7
